{
  "required": true,
  "minVersion": "0.8",
  "package": "me.grian.griansbetamod.mixin",
  "compatibilityLevel": "JAVA_17",
  "mixins": [
    "breakingspeedaxe.AxeItemMixin",
    "breakingspeedpickaxe.PickaxeItemMixin",
    "carpetedstairs.StairsBlockMixin",
    "charcoaltexture.CoalItemMixin",
    "croptrampling.FarmlandBlockMixin",
    "fencehitbox.FenceBlockMixin",
    "itemenhancements.CropBlockMixin",
    "itemenhancements.LogBlockMixin",
    "itemenhancements.OreBlockMixin",
    "itemenhancements.StoneBlockMixin",
    "itemenhancements.ToolItemMixin",
    "lapisspeedboost.PlayerEntityMixin",
    "lapisspeedboost.WorldMixin",
    "stackcrafting.CraftingResultSlotMixin",
    "stackcrafting.ScreenHandlerMixin",
    "stackcrafting.StationShapedRecipeMixin",
    "stairsdrop.StairsBlockMixin"
  ],
  "client": [
    "ClientNetworkHandlerAccessor",
    "debugbiome.InGameHudMixin",
    "netherglassrender.ChunkBuilderMixin"
  ],
  "injectors": {
    "defaultRequire": 1
  },
  "server": [
    "ServerPlayerEntityAccessor"
  ]
}
